.editorconfig
.env
.gitignore
.travis.yml
LICENSE
MANIFEST.in
Pipfile
Pipfile.lock
README.md
setup.py
tox.ini
brewblox_datastore/__init__.py
brewblox_datastore/__main__.py
brewblox_datastore/datastore.py
brewblox_datastore.egg-info/PKG-INFO
brewblox_datastore.egg-info/SOURCES.txt
brewblox_datastore.egg-info/dependency_links.txt
brewblox_datastore.egg-info/requires.txt
brewblox_datastore.egg-info/top_level.txt
docker/.gitignore
docker/amd/Dockerfile
docker/arm/Dockerfile
test/__init__.py
test/conftest.py
test/test_datastore.py
test/test_main.py